openai_chat/__init__.py
openai_chat/chat.py
openai_chat/main.py
openai_chat-0.0.2.dist-info/METADATA
openai_chat-0.0.2.dist-info/WHEEL
openai_chat-0.0.2.dist-info/entry_points.txt
openai_chat-0.0.2.dist-info/RECORD
